cloudglancer/__init__.py
cloudglancer/scatter.py
cloudglancer-0.1.0.dist-info/licenses/LICENSE
cloudglancer-0.1.0.dist-info/METADATA
cloudglancer-0.1.0.dist-info/WHEEL
cloudglancer-0.1.0.dist-info/top_level.txt
cloudglancer-0.1.0.dist-info/RECORD
